{"title": "Indian Government donates 55 buses to Sri Lanka", "content": ["Onlanka News \u2013 By Janaka Alahapperuma The Government of India has promised to donate 55 buses to schools, social and other educational institutes and non government organizations to boost the educational facilities and also uplift the transport facilities in the rural areas of Sri Lanka. As a part of this new scheme two buses were\u2026 "], "link": "https://www.onlanka.com/news/indian-government-donates-55-buses-to-sri-lanka.html", "date_published": "October 5, 2010", "category": "Local News"}