{"title": "Commonwealth Telecommunications Organization forum: Lanka emerging as telecom hub \u2013 President", "content": ["Daily News \u2013 By Rasika Somarathna Sri Lanka today is among the most widely connected countries and societies in the Asian region. It is emerging as the telecom hub of the South Asian region, President Mahinda Rajapaksa said yesterday. Addressing the eighth annual Forum and the 50th Council Meeting of the Commonwealth Telecommunications Organization (CTO)\u2026 "], "link": "https://www.onlanka.com/news/commonwealth-telecommunications-organization-forum-lanka-emerging-as-telecom-hub-president.html", "date_published": "September 14, 2010", "category": "Local News"}