{"title": "Rain ruins Sri Lanka celebrations marking Tigers\u2019 defeat", "content": ["COLOMBO (AFP) \u2013 Heavy rains forced Sri Lanka to postpone ceremonies on Tuesday marking the defeat of the Tamil Tiger rebels one year ago and to remember soldiers who died in the fighting. \u201cThe government has decided to postpone the war heroes\u2019 commemoration ceremony which was due to be held at the War Heroes\u2019 Monument\u2026 "], "link": "https://www.onlanka.com/news/rain-ruins-sri-lanka-celebrations-marking-tigers-defeat.html", "date_published": "May 19, 2010", "category": "Local News"}