{"title": "President Rajapaksa pays a surprise visit to the parliament", "content": ["Onlanka News \u2013 By Janaka Alahapperuma \u2013 (Pix by: Sudath Silva) President Mahinda Rajapaksa paid a surprise visit to the parliament which convened to pass the State of Emergency this afternoon on 6th April. The dissolved parliament met today to extend the State of Emergency by another month. The 6th parliament of Sri Lanka was\u2026 "], "link": "https://www.onlanka.com/news/president-rajapaksa-pays-a-surprise-visit-to-the-parliament.html", "date_published": "April 8, 2010", "category": "Local News"}