{"title": "President unveils Sri Anandaramaya pinnacle in Kalutara", "content": ["President Mahinda Rajapaksa will ceremonially unveil the pinnacle of the newly constructed cetiya at Sri Anandaramaya in Maha Heenatiyangala village in Kalutara South today. The statue made out of rock, five feet in height and in Abaya and Kataka mudra is surrounded by four stone pillars representing four noble truths of worldly life leading to\u2026 "], "link": "https://www.onlanka.com/news/president-unveils-sri-anandaramaya-pinnacle-in-kalutara.html", "date_published": "March 16, 2010", "category": "Local News"}