{"title": "Let\u2019s determine to rise as One Country \u2013 One Nation in this New Year \u2013 President", "content": ["\u201cLet\u2019s determine to rise as One Country \u2013 One Nation unhindered by divisions or disparities, but genuine peace and equality, and to build a drug-free, alcohol-free country in the New Year commencing today\u201d, said President Maithripala Sirisena."], "link": "https://www.onlanka.com/news/lets-determine-to-rise-as-one-country-one-nation-in-this-new-year-president.html", "date_published": "April 13, 2016", "category": "Local News"}