{"title": "Sri Lankan president seeks to win back EU relief on garment exports", "content": ["Sri Lankan President Maithripala Sirisena visits Germany on Monday, seeking political support in a fight to reinstate a trade concession for garment exports, the government said, after the European Union abolished the measure six years ago."], "link": "https://www.onlanka.com/news/sri-lankan-president-seeks-to-win-back-eu-relief-on-garment-exports.html", "date_published": "February 16, 2016", "category": "Local News"}