{"title": "Abduction of youth: Legal action against Hirunika if evidence found \u2013 Police Spokesman", "content": ["The Police would not hesitate to take legal action against Parliamentarian Hirunika Premachandra if the investigations found evidence to the effect that she had aided and abetted the recent abduction of a youth, said ASP Ruwan Gunasekara yesterday."], "link": "https://www.onlanka.com/news/abduction-of-youth-legal-action-against-hirunika-if-evidence-found-police-spokesman.html", "date_published": "December 29, 2015", "category": "Local News"}