{"title": "A little light administrative duty for Sri Lanka\u2019s new hangmen", "content": ["Sri Lanka said on Wednesday it has hired two new executioners to replace the previous hangman, who quit soon after seeing the gallows for the first time, even though capital punishment has not been carried out there for almost 40 years."], "link": "https://www.onlanka.com/news/a-little-light-administrative-duty-for-sri-lankas-new-hangmen.html", "date_published": "October 15, 2015", "category": "Local News"}