{"title": "Sri Lanka v New Zealand: first game of Cricket World Cup at Hagley Oval in Christchurch", "content": ["The wait is finally over, with co-hosts New Zealand taking on Sri Lanka in the first match of the 2015 World Cup. The Black Caps go into the tournament with an unusually large amount of expectation on their shoulders following a superb run of performances over the past few months."], "link": "https://www.onlanka.com/news/sri-lanka-v-new-zealand-first-game-of-cricket-world-cup-at-hagley-oval-in-christchurch.html", "date_published": "February 14, 2015", "category": "Sports News"}