{"title": "Chinese President Congratulates Sri Lanka President Maithripala Sirisena", "content": ["Chinese President Xi Jinping Friday sent a congratulatory message to Maithripala Sirisena on his election as Sri Lanka\u2019s new head of state, pledging to promote the strategic cooperative partnership between the two countries\u2026. "], "link": "https://www.onlanka.com/news/chinese-president-congratulates-sri-lanka-president-maithripala-sirisena.html", "date_published": "January 9, 2015", "category": "Local News"}