{"title": "Packer plan for Sri Lanka Crown casino faces fresh delay on legal hitch \u2013 minister", "content": ["Australian gambling tycoon James Packer\u2019s Crown Ltd is facing months of new delays in building a planned $400 million Sri Lanka hotel and casino resort due to unspecified legal issues, a government minister said on Wednesday, Reuters news agency reports\u2026. "], "link": "https://www.onlanka.com/news/packer-plan-for-sri-lanka-crown-casino-faces-fresh-delay-on-legal-hitch-minister.html", "date_published": "August 28, 2014", "category": "Local News"}