{"title": "To retrieve Kachatheevu we have to go to war with Sri Lanka \u2013 Indian AG", "content": ["A week before hearing on petitions by Tamil Nadu chief minister J Jayalalithaa and her arch rival M Karunanidhi seeking retrieval of Kachatheevu Island from Sri Lanka, attorney general Mukul Rohatgi on Tuesday told the Supreme Court that the task was impossible\u2026. "], "link": "https://www.onlanka.com/news/to-retrieve-kachatheevu-we-have-to-go-to-war-with-sri-lanka-indian-ag.html", "date_published": "August 27, 2014", "category": "Local News"}