{"title": "Action from the Richest Religion : Vatican can wipe out entire Third World debt & poverty", "content": ["The Vatican City is a land locked state inside the city of Rom, Italy and governed by the Pope (Bishop of Rome). It is the world\u2019s smallest sovereign on just 110 acres. The Pope is not only head of 2.3billion people but he is also head of a global financial empire. The Vatican that promotes\u2026 "], "link": "https://www.onlanka.com/news/action-from-the-richest-religion-vatican-can-wipe-out-entire-third-world-debt-poverty.html", "date_published": "July 29, 2014", "category": "Local News"}