{"title": "UNP: Arrest those who assisted BBS in commiting crimes against Muslims", "content": ["The UNP yesterday accused the government of using the Official Secrets Act to cover up the involvement of three intelligence officers in last weeks Bodu Bala Sena (BBS)-led attacks on Muslims in Aluthgama and Beruwela\u2026. "], "link": "https://www.onlanka.com/news/unp-arrest-those-who-assisted-bbs-in-commiting-crimes-against-muslims.html", "date_published": "June 28, 2014", "category": "Local News"}