{"title": "State Vesak Festival in Polonnaruwa", "content": ["The annual State Vesak Festival 2014 will be held centred around the Polonnaruwa district throughout the Vesak Week under the patronage of Prime Minister D.M. Jayaratne. Buddhasasana and Religious Affairs Ministry officials are making arrangements to hold the festival on a grand scale under the guidance of the Prime Minister who is also the Buddha\u2026 "], "link": "https://www.onlanka.com/news/state-vesak-festival-in-polonnaruwa.html", "date_published": "May 9, 2014", "category": "Local News"}