{"title": "Malaysian police deny al-Qaeda links to MH370", "content": ["Malaysian police on Sunday rejected a British report linking the missing Malaysian flight with al-Qaeda, describing it as \u201crubbish.\u201d Earlier, it was reported that a group of eleven suspected terrorists with links to al-Qaeda were arrested on suspicion of being involved in the disappearance of Malaysian flight MH370 and were being interrogated yesterday\u2026. "], "link": "https://www.onlanka.com/news/malaysian-police-deny-al-qaeda-links-to-mh370.html", "date_published": "May 5, 2014", "category": "Foreign News"}