{"title": "ISI agent arrest in Chennai significant \u2013 Terrorism expert", "content": ["Sri Lankan terrorism expert, Dr Rohan Gunaratna, considers the arrest of suspected Lankan Muslim terrorist Zakir Hussain in Chennai on Tuesday, and the busting of his outfit in Tamil Nadu as being \u201cvery significant\u201d for the entire South Asian region\u2026. "], "link": "https://www.onlanka.com/news/isi-agent-arrest-in-chennai-significant-terrorism-expert.html", "date_published": "May 3, 2014", "category": "Local News"}