{"title": "Sri Lankan military official suspended over \u2018offensive\u2019 behavior in London", "content": ["Sri Lanka\u2019s Ministry of Foreign Affairs says the Minister Counsellor (Defence) attached to the Sri Lanka High Commission in London has been suspended with immediate effect and that inquiries will be initiated into the alleged incident involving him."], "link": "https://www.onlanka.com/news/sri-lankan-military-official-suspended-over-offensive-behavior-in-london.html", "date_published": "February 7, 2018", "category": "Local News"}