{"title": "Britain joins call for UN to investigate alleged war crimes in Sri Lanka", "content": ["David Cameron\u2019s office says decision taken after Sri Lanka failed to conduct its own inquiry into civil war Britain is to join the US and three other countries in pushing for a full international inquiry into alleged war crimes in Sri Lanka after the government there failed to satisfy international calls for a such an\u2026 "], "link": "https://www.onlanka.com/news/britain-joins-call-for-un-to-investigate-alleged-war-crimes-in-sri-lanka.html", "date_published": "March 10, 2014", "category": "Local News"}