{"title": "JHU slams Hakeem\u2019s racist policies", "content": ["The Jathika Hela Urumaya (JHU) has lambasted Minister of Justice, Rauff Hakeem\u2019s interventions in the legal education system as an attempt to bring about the \u2018Muslimization\u2019 of the legal sphere, adding that this insidious plan was a conspiracy on the part of the Minister\u2026. "], "link": "https://www.onlanka.com/news/jhu-slams-hakeems-racist-policies.html", "date_published": "February 25, 2014", "category": "Local News"}