{"title": "Sri Lanka complete whitewash after Kusal ton", "content": ["Sri Lanka 246 for 4 (Kusal 106*, Chandimal 64) beat Bangladesh 240 for 8 (Mominul 60, Prasad 3-49) by six wickets With Sri Lanka missing their three senior batsmen, the dead rubber was supposed to be a big test for the younger set. They came through, with Kusal Perera hitting his maiden international century and\u2026 "], "link": "https://www.onlanka.com/news/sri-lanka-complete-whitewash-after-kusal-ton.html", "date_published": "February 23, 2014", "category": "Sports News"}