{"title": "Four Rajiv Gandhi killers, including Nalini Sriharan, to be freed, decides Tamil Nadu government", "content": ["Chennai: The Tamil Nadu government has decided to release three men and one woman convicted of killing former prime minister Rajiv Gandhi in 1991. The death sentence of the men was commuted to life in prison by the Supreme Court yesterday\u2026. "], "link": "https://www.onlanka.com/news/four-rajiv-gandhi-killers-including-nalini-sriharan-to-be-freed-decides-tamil-nadu-government.html", "date_published": "February 19, 2014", "category": "Foreign News"}