{"title": "Sri Lanka rupee weaker on importer dlr demand; premiums up", "content": ["(Reuters) \u2013 The Sri Lankan rupee traded weaker on Thursday on importer dollar demand which outpaced thin greenback sales by exporters, forcing banks to switch to forward trades, dealers said. Dealers said the forward market was active as banks did not trade the spot rupee above 130.85 per dollar \u2014 a level seen as desirable\u2026 "], "link": "https://www.onlanka.com/news/sri-lanka-rupee-weaker-on-importer-dlr-demand-premiums-up.html", "date_published": "February 13, 2014", "category": "Local News"}