{"title": "UN Assistant Secretary General and UNDP Asia Pacific Director meets President Rajapaksa", "content": ["\u2013 by Janaka Alahapperuma \u2013 Assistant Secretary General of the United Nations and Assistant Administrator and Director of the United Nations Development Programme (UNDP) and Regional Bureau for Asia and the Pacific, Mr Haoliang Xu called on President Mahinda Rajapaksa at Temple Trees this evening on 12 February\u2026. "], "link": "https://www.onlanka.com/news/un-assistant-secretary-general-and-undp-asia-pacific-director-meets-president-rajapaksa.html", "date_published": "February 13, 2014", "category": "Local News"}