{"title": "Indian War Crimes in Sri Lanka: IPKF Massacre of Tamil Doctors and Nurses inside Jaffna Hospital", "content": ["\u2013 by Shenali D Waduge \u2013 \u201cThis massacres is worse than My Lai. Then American troops simply ran amok. In the Sri Lankan village, the Indians seem to have been more systematic; the victims being forced to lie down, and then shot in the back\u2019. This was the editorial of the UK Daily Telegraph in\u2026 "], "link": "https://www.onlanka.com/news/indian-war-crimes-in-sri-lanka-ipkf-massacre-of-tamil-doctors-and-nurses-inside-jaffna-hospital.html", "date_published": "February 3, 2014", "category": "Local News"}