{"title": "Gone like a shot: Why did Sri Lanka reinstate alcohol ban for women?", "content": ["Even in ultra-conservative Saudi Arabia, women will finally get the right to drive cars this year. Compare that to Sri Lanka, where women recently won the right to buy a drink at a bar \u2013 or rather had won it, until it was revoked just days later."], "link": "https://www.onlanka.com/news/gone-like-a-shot-why-did-sri-lanka-reinstate-alcohol-ban-for-women.html", "date_published": "January 21, 2018", "category": "Local News"}