{"title": "15,000 tonnes of substandard petrol imported", "content": ["Ananda Palitha, the secretary of the Ceylon Petroleum Corporation (CPC) chapter of the Jathika Sevaka Sangamaya (JSS) alleged that a consignment of 15,000 tonnes of substandard petrol (90 octane) had been imported and was scheduled to be pumped to the Muturajawela Oil Storage facility on Sunday\u2026. "], "link": "https://www.onlanka.com/news/15000-tonnes-of-substandard-petrol-imported.html", "date_published": "October 2, 2013", "category": "Local News"}