{"title": "Sri Lanka sees new threats of terrorism, Muslim extremism", "content": ["(Reuters) \u2013 Sri Lanka, under heavy pressure to end human rights abuses four years after the end of a brutal civil war with Tamil Tiger rebels, said on Tuesday it faced a new threat of terrorism and Muslim extremism. The comments came three days after U.N. Rights Commissioner Navi Pillay said people were still suffering\u2026 "], "link": "https://www.onlanka.com/news/sri-lanka-sees-new-threats-of-terrorism-muslim-extremism.html", "date_published": "September 4, 2013", "category": "Local News"}