{"title": "I am at loss to understand how I became a suspect: Ravi Karunanayake", "content": ["UNP MP Ravi Karunanayake, against whom the Bond Commission presses bribery charges, said he was at a loss to understand how he turned up as a suspect since the Central Bank and the State Banks did not remain under his purview."], "link": "https://www.onlanka.com/news/i-am-at-loss-to-understand-how-i-became-a-suspect-ravi-karunanayake.html", "date_published": "January 5, 2018", "category": "Local News"}