{"title": "Presidential proclamation for Northern PC polls", "content": ["President Mahinda Rajapaksa yesterday issued a proclamation calling for the holding of elections to the Northern Provincial Council. Commissioner General of Elections Mahinda Deshapriya was officially notified about this yesterday, said Presidential Spokesman and senior journalist Mohan Samaranayake\u2026. "], "link": "https://www.onlanka.com/news/presidential-proclamation-for-northern-pc-polls.html", "date_published": "July 6, 2013", "category": "Local News"}