{"title": "UK warns Sri Lanka on abuses before Commonwealth summit", "content": ["LONDON (Reuters) \u2013 Britain said on Wednesday there would be \u201cconsequences\u201d for Sri Lanka if its leaders did not address international concerns over human rights abuses, ahead of a Commonwealth summit scheduled to be held in Colombo in November\u2026. "], "link": "https://www.onlanka.com/news/uk-warns-sri-lanka-on-abuses-before-commonwealth-summit.html", "date_published": "May 16, 2013", "category": "Local News"}