{"title": "New Democratic Party campaign to pressure government to boycott Commonwealth summit in Sri Lanka", "content": ["\u2013 Submitted by Walter Jayawardhana \u2013 OTTAWA \u2013 The NDP is putting pressure on the Harper government to boycott this year\u2019s Commonwealth summit in Sri Lanka as a protest against the country\u2019s human rights record\u2026. "], "link": "https://www.onlanka.com/news/new-democratic-party-campaign-to-pressure-government-to-boycott-commonwealth-summit-in-sri-lanka.html", "date_published": "April 26, 2013", "category": "Local News"}