{"title": "Indian Government\u2019s Injustice to IPKF in India\u2019s Vietnam", "content": ["\u2013 by Shenali Waduge \u2013 The arrival of over 70,000 Indian Peace Keeping Force troops to Sri Lanka followed the signing of the Indo-Lanka Peace Accord on 29 July 1987. Their task was significant for ironically the IPKF was to disarm the very militants that India had provided covert training & arms to. In other\u2026 "], "link": "https://www.onlanka.com/news/indian-governments-injustice-to-ipkf-in-indias-vietnam.html", "date_published": "April 11, 2013", "category": "Local News"}