{"title": "WHERE WAS DMK\u2019S CONSCIENCE SLUMBERING WHEN SRI LANKAN HUMAN RIGHTS WERE ACTUALLY VIOLATED ASKS TIMES OF INDIA", "content": ["\u2013 By Walter Jayawardhana \u2013 The Times of India in a hard hitting editorial written on the threat of walk out by the Indian Central government\u2019s coalition ally the DMK on the issue of alleged human rights violations by Sri Lanka questioned where it was slumbering when the violations were actually committed\u2026. "], "link": "https://www.onlanka.com/news/where-was-dmks-conscience-slumbering-when-sri-lankan-human-rights-were-actually-violated-asks-times-of-india.html", "date_published": "March 20, 2013", "category": "Local News"}