{"title": "Why are our children disgracing the country by joining the anti-Sri Lanka lobbies?", "content": ["By Ernest Perera It saddens me to see how many of our children who are now grown up men and women holding important posts opt to take the path of ridiculing the nation that they were born in, the nation they grew up and a nation that holds good and bad memories for their parents\u2026 "], "link": "https://www.onlanka.com/news/why-are-our-children-disgracing-the-country-by-joining-the-anti-sri-lanka-lobbies.html", "date_published": "February 27, 2013", "category": "Local News"}