{"title": "Attack on Bank of Ceylon Branch in Chennai", "content": ["The Sri Lanka Deputy High Commission in Chennai\u00a0 has reported that a\u00a0 mob\u00a0 of\u00a0 around 15 people , carrying iron\u00a0 rods, wooden sticks\u00a0 and knives had entered\u00a0 the\u00a0 office of the \u00a0Bank of Ceylon Branch \u00a0at Poonamallee High Road\u00a0 in Chennai at 1.30 p.m. on 7th February 2013. The mob had \u00a0overpowered\u00a0 two police personnel\u00a0\u2026 "], "link": "https://www.onlanka.com/news/attack-on-bank-of-ceylon-branch-in-chennai.html", "date_published": "February 8, 2013", "category": "Local News"}