{"title": "Sri Lanka in Super Six after another historic win", "content": ["Sri Lanka 282 for 5 (Rasangika 84, Siriwardene 59, Kaushalya 56*, Mendis 55) beat India 144 (Malhotra 38, Seneviratna 2-10) by 138 runs Less than a week ago, few Sri Lankans apart from the players\u2019 families and board officials knew the country had a women\u2019s cricket team, according to the captain Shashikala Siriwardene. On February\u2026 "], "link": "https://www.onlanka.com/news/sri-lanka-in-super-six-after-another-historic-win.html", "date_published": "February 6, 2013", "category": "Sports News"}