{"title": "Press Statement regarding International Bar Association Issue", "content": ["Following the detection of inaccurate information contained in the visa applications of the 4 member delegation representing the International Bar Association (IBA), which had unilaterally scheduled a visit to Sri Lanka, regrettably the Government of Sri Lanka was constrained to withdraw visas issued through the ETA system for 3 applicants and the other by a\u2026 "], "link": "https://www.onlanka.com/news/press-statement-regarding-international-bar-association-issue.html", "date_published": "February 4, 2013", "category": "Local News"}