{"title": "HINDU SAYS RAJAPAKSA HAS PLACED HIS INTEREST OVER THAT OF THE COUNTRY", "content": ["By Walter Jayawardhana India\u2019s influential newspaper the Hindu said in a hard hitting editorial that the Sri Lanka President Mahinda Rajapaksa has placed his and and his regime\u2019s interest over that of the country and its institutions when the Sri Lankan Chief Justice Dr. Shirani Bandaranayaka was impeached and replaced\u2026. "], "link": "https://www.onlanka.com/news/hindu-says-rajapaksa-has-placed-his-interest-over-that-of-the-country.html", "date_published": "January 17, 2013", "category": "Local News"}