{"title": "Civilian Casualties \u2013 International Laws and Sri Lanka Bashing", "content": ["U.S. Army in\u00a0Afghanistan By Shenali Waduge How many wonder as to the practicality of ONLY soldiers going through all the rules and regulations in an intense battleground situation when the terrorist enemy are not signatory to any international humanitarian laws and possesses the means to retaliate with brutality? When the enemy thrives and survives on\u2026 "], "link": "https://www.onlanka.com/news/civilian-casualties-international-laws-and-sri-lanka-bashing.html", "date_published": "November 26, 2012", "category": "Local News"}