{"title": "CHANDRA WICKRAMASINGHE SAYS SRI LANKA RED RAIN SIMILAR TO KERALA ONES DEFINITELY WITH COSMIC CONNECTIONS", "content": ["Onlanka News \u2013 by Walter Jayawardhana Professor Chandra Wickramasinghe, Director of the Astrobiological Center at the Buckingham University, England said the recent phenomenon of red rain in Sri Lanka is reportedly similar to the red rain in Kerala in 2011 and 2009 which definitely had some cosmic connection\u2026. "], "link": "https://www.onlanka.com/news/chandra-wickramasinghe-says-sri-lanka-red-rain-similar-to-kerala-ones-definitely-with-cosmic-connections.html", "date_published": "November 18, 2012", "category": "Local News"}