{"title": "President to unveil UPFA govt\u2019s eighth budget", "content": ["President Mahinda Rajapaksa will present Independent Sri Lanka\u2019s 66th budget in Parliament today. President Rajapaksa who assumed office as the fifth Executive President on November 17, 2005, presented his first budget the same year. This will be the eighth budget presented by President Rajapaksa in his capacity as the Finance and Planning Minister\u2026. "], "link": "https://www.onlanka.com/news/president-to-unveil-upfa-govts-eighth-budget.html", "date_published": "November 8, 2012", "category": "Local News"}