{"title": "Minister Peiris meets the new External Affairs Minister of India", "content": ["Minister of External Affairs G. L. Peiris who is in New Delhi for the 12th Meeting of the Council of Ministers of the Indian Ocean Rim Association for Regional Cooperation (IOR-ARC) that is currently chaired by India, met the Minister of External Affairs of India, Salman Khurshid, on 2 November. This was the first meeting\u2026 "], "link": "https://www.onlanka.com/news/minister-peiris-meets-the-new-external-affairs-minister-of-india.html", "date_published": "November 3, 2012", "category": "Local News"}