{"title": "Sri Lanka securities regulator says to quit before Friday", "content": ["(Reuters) \u2013 The head of Sri Lanka\u2019s Securities and Exchange Commission said on Tuesday he will resign this week, saying investors who were being investigated for market manipulation had made false allegations against him. Tilak Karunaratne has been pushing for investigations into stock market malpractices, including so-called pump-and-dump deals in which investors are lured into\u2026 "], "link": "https://www.onlanka.com/news/sri-lanka-securities-regulator-says-to-quit-before-friday.html", "date_published": "August 15, 2012", "category": "Local News"}