{"title": "CERTAINLY THERE SHOULD BE A SUBSURFACE DOMAIN OF WATER AND MICROBES IN IT \u2013 CHANDRA WICKRAMASINGHE", "content": ["Onlanka News \u2013 by Walter Jayawardhana If moon\u2019s Southern polar crater ice is confirmed it should lead to the discovery of life on the moon says a leading astrobiologist\u2026. "], "link": "https://www.onlanka.com/news/certainly-there-should-be-a-subsurface-domain-of-water-and-microbes-in-it-chandra-wickramasinghe.html", "date_published": "June 24, 2012", "category": "Local News"}