{"title": "Colombo to be transformed into a truly world class city \u2013 Secretary Defence", "content": ["\u201cThe Metro Colombo Urban Development Project and its successful implementation, together with other initiatives of the Government to develop Colombo, will help transform this city into a truly world class one\u201d, said Secretary to the Ministry of Defence and Urban Development Mr. Gotabaya Rajapaksa today morning (May 28)\u2026. "], "link": "https://www.onlanka.com/news/colombo-to-be-transformed-into-a-truly-world-class-city-secretary-defence.html", "date_published": "May 28, 2012", "category": "Local News"}