{"title": "SUPREME COURT TAKES OVER MERCY PLEAS OF \u201cRAJIV KILLERS\u201d FROM MADRAS HIGH COURT", "content": ["Onlanka News \u2013 By Walter Jayawardhana The Supreme Court today decided to adjudicate itself the mercy pleas of Rajiv Gandhi killers against their death penalty due to the delay of over 11 years in deciding their mercy petitions by the President Pratiba Patil, reported the Pioneer Indian Prime Minister Rajiv Gandhi was killed by a\u2026 "], "link": "https://www.onlanka.com/news/supreme-court-takes-over-mercy-pleas-of-rajiv-killers-from-madras-high-court.html", "date_published": "May 1, 2012", "category": "Foreign News"}