{"title": "US move against Sri Lanka an undue meddling in country\u2019s sovereignty \u2013 Rev Malcolm Cardinal Ranjith", "content": ["Rev.\u00a0 Malcolm Cardinal Ranjith of Colombo\u00a0 says that presenting of a resolution against Sri Lanka by the United States Government at the United Nations Human Right Council (UNHRC) session in Geneva is an undue meddling in the sovereignty and integrity\u00a0 of Sri Lanka\u2026 "], "link": "https://www.onlanka.com/news/us-move-against-sri-lanka-an-undue-meddling-in-countrys-sovereignty-rev-malcolm-cardinal-ranjith.html", "date_published": "February 27, 2012", "category": "Local News"}