{"title": "Hard-hitting Perera seals first win for Sri Lanka", "content": ["Sri Lanka 304 for 5 (Dilshan 87, Perera 69*, Chandimal 59) beat South Africa 299 for 7 (de Villiers 96, Smith 68) by five wickets It took Sri Lanka three consecutive defeats to get their batsmen firing in unison. Tillakaratne Dilshan finally played with freedom to give the chase momentum, Dinesh Chandimal anchored it in\u2026 "], "link": "https://www.onlanka.com/news/hard-hitting-perera-seals-first-win-for-sri-lanka.html", "date_published": "January 21, 2012", "category": "Sports News"}