{"title": "British Govt. comments on LLRC report", "content": ["The Parliamentary Under-Secretary of State for Foreign and Commonwealth Affairs, Alistair Burt stated: I would like to inform the House of the Government\u2019s views on the Sri Lankan Lessons Learnt and Reconciliation Commission\u2019s (LLRC) report, which was published on December 16, 2011. The LLRC was established in May 2010 to look into the conflict between\u2026 "], "link": "https://www.onlanka.com/news/british-govt-comments-on-llrc-report.html", "date_published": "January 13, 2012", "category": "Local News"}