{"title": "Former LTTE official recounts last stages of war: LTTE did not consider age for combat", "content": ["The LTTE holed up in the ever-diminishing territory in northern Sri Lanka forcibly recruited children to take part in final defences against government troops, according to a former senior LTTE official, the British newspaper, The Independent reported\u2026. "], "link": "https://www.onlanka.com/news/former-ltte-official-recounts-last-stages-of-war-ltte-did-not-consider-age-for-combat.html", "date_published": "December 13, 2011", "category": "Local News"}