{"title": "Colombo citizens have taken their individual decisions \u2013 Moragoda", "content": ["UPFA candidate for Colombo Milinda Moragoda while thanking those Colombo residents and well-wishers who placed their trust in him observed that the \u201cincomplete nature of the mandate given by the people of Colombo shows there is no agreement on policies that would take us forward\u2026. "], "link": "https://www.onlanka.com/news/colombo-citizens-have-taken-their-individual-decisions-moragoda.html", "date_published": "October 13, 2011", "category": "Local News"}