{"title": "Dilshan\u2019s maiden T20 ton sinks Aussies", "content": ["Tillakaratne Dilshan hit a maiden century off just 57 balls and Dilruwan Perera took three wickets to lead Sri Lanka to a 35-run win against Australia in the first Twenty20 match on Saturday. Dilshan hit five sixes and 12 boundaries for an unbeaten 104 as Sri Lanka ended on 198-3 in 20 overs\u2026. "], "link": "https://www.onlanka.com/news/dilshan%e2%80%99s-maiden-t20-ton-sinks-aussies.html", "date_published": "August 7, 2011", "category": "Sports News"}