{"title": "BCCI fears Modi role in Sri Lankan Premier League", "content": ["The spectre of Lalit Modi continues to haunt the Indian cricket board. According to top sources, BCCI has refused to let Indian cricketers play in the upcoming Sri Lankan Premier League because it suspects that the former IPL czar is behind the new T20 league\u2026. "], "link": "https://www.onlanka.com/news/bcci-fears-modi-role-in-sri-lankan-premier-league.html", "date_published": "June 20, 2011", "category": "Sports News"}