{"title": "German envoy warns Def. Secy over \u2018police excesses\u2019", "content": ["German Ambassador Jens Plotner has warned Defence Secretary Gotabhaya Rajapaksa over what he calls disproportionate use of police force during Monday\u2019s clashes between the police and a large group of workers at the Katunayake Export Processing Zone (EPZ)\u2026. "], "link": "https://www.onlanka.com/news/german-envoy-warns-def-secy-over-%e2%80%98police-excesses%e2%80%99.html", "date_published": "June 3, 2011", "category": "Local News"}