{"title": "Acting true to form: Cashing in on the dead, JVP\u2019s creed \u2013 Minister Dilan Perera", "content": ["\u201cFrom the beginning, the JVP got a person killed and then sold his body and blood stained clothes to gain political advantage. This time a garment worker became their victim. The police blindly assisted the JVP to kill this person,\u201d Foreign Employment and Welfare Minister Dilan Perera said\u2026. "], "link": "https://www.onlanka.com/news/acting-true-to-form-cashing-in-on-the-dead-jvp%e2%80%99s-creed-minister-dilan-perera.html", "date_published": "June 3, 2011", "category": "Local News"}