{"title": "EU rejects intl. probe on Sri Lanka", "content": ["The European Parliament yesterday defeated an attempt by the Socialist group \u201cto seek the immediate establishment of an international justice mechanism\u201d on Sri Lanka, the Sri Lankan Embassy in Brussels said. The eventual resolution adopted instead during an \u2018urgency\u2019 debate called by the Socialist and Green parties at the Strassbourg Plenary session to draw attention\u2026 "], "link": "https://www.onlanka.com/news/eu-rejects-intl-probe-on-sri-lanka.html", "date_published": "May 13, 2011", "category": "Local News"}