{"title": "India the top team but not the best host", "content": ["Three days after the World Cup final, officials from Sri Lanka are not happy with the level of courtesy extended to their President Mahinda Rajapaksa during his trip to Mumbai to watch the final. Though no official complaint has been lodged with the Indian government, they have informally conveyed their displeasure at limited tickets made\u2026 "], "link": "https://www.onlanka.com/news/india-the-top-team-but-not-the-best-host.html", "date_published": "April 6, 2011", "category": "Local News"}