{"title": "India end Australia reign, set up Pakistan showdown", "content": ["NEW DELHI (AFP) \u2013 India swept three-time defending champions Australia out of the World Cup on Thursday to set up a semi-final showdown against bitter rivals Pakistan and heap more pressure on Ricky Ponting. India\u2019s five-wicket triumph in Ahmedabad means they will tackle Pakistan, who reached the last four with a crushing 10-wicket win over\u2026 "], "link": "https://www.onlanka.com/news/india-end-australia-reign-set-up-pakistan-showdown.html", "date_published": "March 25, 2011", "category": "Sports News"}