{"title": "Sri Lanka: Protection of Human Right enshrined in the National Action Plan", "content": ["Minister Samarasinghe briefs the16th UNHRC Sessions Sri Lankan Government has taken considerable action to facilitate the restoration of normal lives of the returning IDPs in the northern province of the country.. Sri Lankan Minister Mahinda Samarasinghe who is in-charge of the subject Human Right issues in the Cabinet has said that they had now begun\u2026 "], "link": "https://www.onlanka.com/news/sri-lanka-protection-of-human-right-enshrined-in-the-national-action-plan.html", "date_published": "March 1, 2011", "category": "Local News"}