{"title": "Indian fishermen issue: Preventive measures for sustainable solution \u2013 President", "content": ["Preventive measures are necessary to find a sustainable solution for the issue of Indian fishermen entering Sri Lankan waters, stated President Mahinda Rajapaksa at a meeting with the editors of government and private media institutes of Sri Lanka, held today (22) at Temple Trees\u2026. "], "link": "https://www.onlanka.com/news/indian-fishermen-issue-preventive-measures-for-sustainable-solution-%e2%80%93-president.html", "date_published": "February 22, 2011", "category": "Local News"}