{"title": "Imported eggs and chicken arriving today, coconuts in three days \u2013 Johnston", "content": ["Stocks of imported eggs and chicken will reach Sri Lanka sometime in the evening today (December 23) while the stocks will be ready for distribution by tomorrow, Cooperatives and Internal Trade Minister Johnston Fernando stated\u2026. "], "link": "https://www.onlanka.com/news/imported-eggs-and-chicken-arriving-today-coconuts-in-three-days-johnston.html", "date_published": "December 23, 2010", "category": "Local News"}