{"title": "Sri Lanka climbs higher in World Prosperity Index", "content": ["(Colombo Lankapuvath) Sri Lanka has climbed 9 positions from 2009 and is ranked 59th among 110 nations, in the World Prosperity Index released today (01). Sri Lanka is well above India, Pakistan and Indonesia representing the Asia Pacific region in the rating for 2010 released by London\u2019s Legatum Institute\u2026. "], "link": "https://www.onlanka.com/news/sri-lanka-climbs-higher-in-world-prosperity-index.html", "date_published": "November 2, 2010", "category": "Local News"}